pyproject.toml
docs/README.md
src/bviz/main.py
src/bviz.egg-info/PKG-INFO
src/bviz.egg-info/SOURCES.txt
src/bviz.egg-info/dependency_links.txt
src/bviz.egg-info/entry_points.txt
src/bviz.egg-info/requires.txt
src/bviz.egg-info/top_level.txt
src/bviz/icons/response.png
src/bviz/icons/tool.png
src/bviz/icons/user.png