Metadata-Version: 2.4
Name: bviz
Version: 0.1.0
Summary: Bedrock Vision visualizes Bedrock Converse API conversations
Author-email: Michael Rowlinson <rowlinsonmike@gmail.com>
Project-URL: Homepage, https://github.com/rowlinsonmike/bviz
Project-URL: Documentation, https://github.com/rowlinsonmike/bviz
Project-URL: Repository, https://github.com/rowlinsonmike/bviz
Requires-Python: >=3.10
Requires-Dist: diagrams>=0.24.4
Requires-Dist: typer>=0.20.0
